<core:FragmentDefinition xmlns="sap.m"
    xmlns:core="sap.ui.core">
   <Table id="table" width="auto"
				items="{ path: '/NotificationGroupSet', filters : { path : 'IsArchived' , operator : 'EQ' , value1 : false }, sorter: { path: 'Id', descending: false } }"
				noDataText="{i18n>tableNoDataText}" busyIndicatorDelay="0" growing="true" growingScrollToLoad="false" growingThreshold="10"
				updateFinished=".onUpdateFinished">
				<headerToolbar>
					<OverflowToolbar>
						<Title id="tableHeader" text="{oModelControl>/Table1Count}" level="H3"/>
						<ToolbarSpacer/>
						<!-- <Button text="{i18n>btnRefresh}" icon="sap-icon://refresh" press="onRefreshView">
							<layoutData>
								<OverflowToolbarLayoutData maxWidth="200px" priority="NeverOverflow"/>
							</layoutData>
						</Button> -->
						<Button text="{i18n>btnAdd}" type="Emphasized" icon="sap-icon://add" press="onAdd">
							<layoutData>
								<OverflowToolbarLayoutData maxWidth="200px" priority="NeverOverflow"/>
							</layoutData>
						</Button>
					</OverflowToolbar>
				</headerToolbar>
				<columns>
					<Column width="57%">
						<Text text="{i18n>colGroupName}"/>
					</Column>
					<Column width="13%">
						<Text text="{i18n>colTotalMembers}"/>
					</Column>
					<Column width="20%">
						<Text text="{i18n>colCreator}"/>
					</Column>
					<Column >
						<Text text="{i18n>colAction}"/>
					</Column>
				</columns>
				<items>
					<ColumnListItem type="Navigation" press="onPressView">
						<cells>
							<Text text="{GroupName}"/>
							<Text text="{TotalMembers}"/>
							<Text text="{= ${CreatorName}=== null ? 'SYSTEM' : ${CreatorName} }"/>
                            <FlexBox >
							<Button icon="sap-icon://edit"  visible="{= ${IsDefault} !== true }" press="onEdit" type="Transparent" tooltip="Edit"/>
							<Button icon="sap-icon://delete" visible="{= ${IsDefault} !== true }" press="onDelete" type="Transparent" tooltip="Delete"/>
                            </FlexBox>
                        </cells>
					</ColumnListItem>
				</items>
			</Table>
</core:FragmentDefinition>
